odoo10_addon_stock_auto_move-10.0.1.0.0-py2.7-nspkg.pth
odoo/addons/stock_auto_move/README.rst
odoo/addons/stock_auto_move/__init__.py
odoo/addons/stock_auto_move/__manifest__.py
odoo/addons/stock_auto_move/data/stock_auto_move_data.xml
odoo/addons/stock_auto_move/demo/stock_auto_move_demo.xml
odoo/addons/stock_auto_move/i18n/ca.po
odoo/addons/stock_auto_move/i18n/de.po
odoo/addons/stock_auto_move/i18n/es.po
odoo/addons/stock_auto_move/i18n/es_MX.po
odoo/addons/stock_auto_move/i18n/fi.po
odoo/addons/stock_auto_move/i18n/fr.po
odoo/addons/stock_auto_move/i18n/hr.po
odoo/addons/stock_auto_move/i18n/it.po
odoo/addons/stock_auto_move/i18n/pt.po
odoo/addons/stock_auto_move/i18n/pt_BR.po
odoo/addons/stock_auto_move/i18n/pt_PT.po
odoo/addons/stock_auto_move/i18n/sl.po
odoo/addons/stock_auto_move/i18n/tr.po
odoo/addons/stock_auto_move/i18n/tr_TR.po
odoo/addons/stock_auto_move/i18n/zh_CN.po
odoo/addons/stock_auto_move/models/__init__.py
odoo/addons/stock_auto_move/models/stock_auto_move.py
odoo/addons/stock_auto_move/tests/__init__.py
odoo/addons/stock_auto_move/tests/test_stock_auto_move.py
odoo/addons/stock_auto_move/views/stock_auto_move_view.xml
odoo10_addon_stock_auto_move-10.0.1.0.0.dist-info/DESCRIPTION.rst
odoo10_addon_stock_auto_move-10.0.1.0.0.dist-info/METADATA
odoo10_addon_stock_auto_move-10.0.1.0.0.dist-info/RECORD
odoo10_addon_stock_auto_move-10.0.1.0.0.dist-info/WHEEL
odoo10_addon_stock_auto_move-10.0.1.0.0.dist-info/metadata.json
odoo10_addon_stock_auto_move-10.0.1.0.0.dist-info/namespace_packages.txt
odoo10_addon_stock_auto_move-10.0.1.0.0.dist-info/top_level.txt
